kllr/__init__.py
kllr/regression_model.py
kllr/regression_plotting.py
kllr-2.0.dist-info/LICENSE
kllr-2.0.dist-info/METADATA
kllr-2.0.dist-info/WHEEL
kllr-2.0.dist-info/top_level.txt
kllr-2.0.dist-info/RECORD
